{
  "_class": "group",
  "do_objectID": "30F9DB87-CCE0-46CE-AD16-CAA7EA07C347",
  "exportOptions": {
    "_class": "exportOptions",
    "exportFormats": [
    ],
    "includedLayerIds": [
    ],
    "layerOptions": 0,
    "shouldTrim": false
  },
  "frame": {
    "_class": "rect",
    "constrainProportions": false,
    "height": 3433,
    "width": 1188,
    "x": 6,
    "y": 0
  },
  "hasClickThrough": false,
  "isFlippedHorizontal": false,
  "isFlippedVertical": false,
  "isLocked": true,
  "isVisible": true,
  "layerListExpandedType": 1,
  "layers": [
    {
      "class": "shapeGroup",
      "id": "63598993-9EC3-4FD2-931B-33363F647059"
    },
    {
      "class": "shapeGroup",
      "id": "98122380-ADDE-4EB0-BE00-1D3F71A4B250"
    },
    {
      "class": "shapeGroup",
      "id": "AA11C4A0-3918-4AA4-931A-4F4B926A3DB8"
    },
    {
      "class": "shapeGroup",
      "id": "7973A667-1BB5-449E-9F5C-6F0BD6EB9006"
    },
    {
      "class": "shapeGroup",
      "id": "FD641B44-7F17-4E39-A0EF-9F67ABAD668C"
    },
    {
      "class": "shapeGroup",
      "id": "31D3193A-CF05-4606-B919-19E99DFBD9F6"
    },
    {
      "class": "shapeGroup",
      "id": "A3B24D22-2A90-4380-8B1C-463C727347BC"
    },
    {
      "class": "shapeGroup",
      "id": "B1BCB4C2-08B0-421D-A58E-B37C1367FF80"
    },
    {
      "class": "shapeGroup",
      "id": "15D4C4AD-3457-4723-A9A1-6A1C15B83456"
    },
    {
      "class": "shapeGroup",
      "id": "C7BC35BC-487A-4408-8D7F-D12E9E516115"
    },
    {
      "class": "shapeGroup",
      "id": "90D8A46C-AFB3-4A37-87E1-D81F2214DDB8"
    },
    {
      "class": "shapeGroup",
      "id": "F19CC725-E234-4977-A829-C9B46251003A"
    }
  ],
  "name": "grid1200",
  "nameIsFixed": true,
  "resizingConstraint": 63,
  "resizingType": 0,
  "rotation": 0,
  "shouldBreakMaskChain": false,
  "style": {
    "_class": "style",
    "endDecorationType": 0,
    "miterLimit": 10,
    "startDecorationType": 0
  },
  "userInfo": {
    "com.animaapp.stc-sketch-plugin": {
      "kModelPropertiesKey": {
      }
    }
  }
}